helpers/__init__.py
helpers/cubes.py
helpers/dates.py
helpers/exceptions.py
helpers/files.py
helpers/map_type_handling.py
helpers/nemo.py
helpers/presentation_objects.py
monitoring/diskusage_rte_scalar.py
monitoring/gitlab.py
monitoring/linear_combination.py
monitoring/map.py
monitoring/markdown.py
monitoring/nemo_all_mean_map.py
monitoring/nemo_time_mean_temporalmap.py
monitoring/nemo_timeseries.py
monitoring/oifs_all_mean_map.py
monitoring/oifs_global_mean_year_mean_timeseries.py
monitoring/oifs_year_mean_temporalmap.py
monitoring/redmine.py
monitoring/scalar.py
monitoring/si3_hemis_point_month_mean_all_mean_map.py
monitoring/si3_hemis_point_month_mean_temporalmap.py
monitoring/si3_hemis_sum_month_mean_timeseries.py
monitoring/simulatedyears_rte_scalar.py
monitoring/temporalmap.py
monitoring/timeseries.py
scriptengine_tasks_ecearth-0.8.0.dist-info/licenses/LICENSE
scriptengine_tasks_ecearth-0.8.0.dist-info/METADATA
scriptengine_tasks_ecearth-0.8.0.dist-info/WHEEL
scriptengine_tasks_ecearth-0.8.0.dist-info/entry_points.txt
scriptengine_tasks_ecearth-0.8.0.dist-info/top_level.txt
scriptengine_tasks_ecearth-0.8.0.dist-info/RECORD
