Metadata-Version: 2.4
Name: scriptengine-tasks-ecearth
Version: 0.8.0
Summary: ScriptEngine tasks for use with the EC-Earth climate model
Author-email: Valentina Schueller <valentina.schueller@gmail.com>, Uwe Fladrich <uwe.fladrich@protonmail.com>
Project-URL: Homepage, https://github.com/uwefladrich/scriptengine-tasks-ecearth
Project-URL: Bug Tracker, https://github.com/uwefladrich/scriptengine-tasks-ecearth/issues
Classifier: Programming Language :: Python :: 3
Classifier: License :: OSI Approved :: GNU General Public License v3 or later (GPLv3+)
Classifier: Operating System :: OS Independent
Requires-Python: >=3.8
License-File: LICENSE
Requires-Dist: scriptengine>=0.8.1
Requires-Dist: pyYAML>=5.1
Requires-Dist: matplotlib>=3.1
Requires-Dist: numpy>=1.18
Requires-Dist: imageio>=2.18
Requires-Dist: scitools-iris>=3.5
Requires-Dist: cartopy>=0.20
Requires-Dist: python-redmine
Requires-Dist: python-gitlab
Dynamic: license-file
